randomstring/__init__.py
randomstring/randomstring.py
Random_String_Maker-2.0.dist-info/METADATA
Random_String_Maker-2.0.dist-info/WHEEL
Random_String_Maker-2.0.dist-info/top_level.txt
Random_String_Maker-2.0.dist-info/RECORD
