Metadata-Version: 2.1
Name: Random-String-Maker
Version: 2.0
Summary: A simple random string generator I built in my free time.
Author: Aidan Hetherington
License: MIT
Platform: UNKNOWN
